tests/__init__.py
tests/functional/__init__.py
tests/functional/conftest.py
tests/functional/test_public_models.py
tests/functional/test_tune_the_model.py
tune_the_model/__init__.py
tune_the_model/cli.py
tune_the_model/resource.py
tune_the_model-0.1.33.dist-info/LICENSE
tune_the_model-0.1.33.dist-info/METADATA
tune_the_model-0.1.33.dist-info/WHEEL
tune_the_model-0.1.33.dist-info/top_level.txt
tune_the_model-0.1.33.dist-info/RECORD
