Metadata-Version: 2.1
Name: tune-the-model
Version: 0.1.33
Summary: beyondml
Home-page: https://github.com/tune-the-model/tune-the-model-py
Download-URL: https://pypi.org/project/beyond.ml/
Author: BeyondML
Author-email: pavel.gavrilov@beyond.ml
License: MIT
Keywords: beyondml,tune-the-model,gpt-3,nlp
License-File: LICENSE
Requires-Dist: pandas (>1.3)
Requires-Dist: requests (>2.10)
Requires-Dist: scikit-learn
